interstate_py/__init__.py
interstate_py/connection_agent.py
interstate_py/control/__init__.py
interstate_py/control/connection_reaper.py
interstate_py/control/worker_task.py
interstate_py/error/__init__.py
interstate_py/error/error_assembly.py
interstate_py/internalio/__init__.py
interstate_py/internalio/data_input_stream.py
interstate_py/internalio/data_output_stream.py
interstate_py/interstate.py
interstate_py/interstate_message.py
interstate_py/interstate_server.py
interstate_py/log_factory.py
interstate_py/multiplex_message.py
interstate_py/reactive/__init__.py
interstate_py/reactive/rx_stream_connection.py
interstate_py/reactive/sending_observer.py
interstate_py/serialization/__init__.py
interstate_py/serialization/serialization.py
interstate_py/stream_connection.py
interstate_py/stream_demultiplexer.py
interstate_py/stream_multiplexer.py
interstate_py/zeromq/__init__.py
interstate_py/zeromq/aio_zmq_server.py
interstate_py/zeromq/inbound_worker.py
interstate_py/zeromq/outbound_worker.py
interstate_py/zeromq/zmsg_assembly.py
interstate_py-1.2.0.dist-info/entry_points.txt
interstate_py-1.2.0.dist-info/WHEEL
interstate_py-1.2.0.dist-info/METADATA
interstate_py-1.2.0.dist-info/RECORD
