Metadata-Version: 2.1
Name: interstate-py
Version: 1.2.0
Summary: 
Author: LeftshiftOne Software GmbH
Author-email: devs@leftshift.one
Requires-Python: >=3.6,<4.0
Classifier: Programming Language :: Python :: 3
Classifier: Programming Language :: Python :: 3.6
Classifier: Programming Language :: Python :: 3.7
Classifier: Programming Language :: Python :: 3.8
Requires-Dist: Rx (>=3.1.0,<4.0.0)
Requires-Dist: aiozmq (>=0.7.1,<0.8.0)
Requires-Dist: janus (>=0.5.0,<0.6.0)
Requires-Dist: pyzmq (>=18.0,<19.0)
